robotpy_rev_digit/__init__.py
robotpy_rev_digit/__version__.py
robotpy_rev_digit/py.typed
robotpy_rev_digit/rev_digit_board.py
robotpy_rev_digit-1.1.0.dist-info/METADATA
robotpy_rev_digit-1.1.0.dist-info/WHEEL
robotpy_rev_digit-1.1.0.dist-info/licenses/LICENSE.txt
robotpy_rev_digit-1.1.0.dist-info/RECORD
