Metadata-Version: 2.4
Name: robotpy-rev-digit
Version: 1.1.0
Summary: A module for controlling the REV Digit Board from RobotPy.
Project-URL: Documentation, https://github.com/cwstryker/robotpy-rev-digit#readme
Project-URL: Issues, https://github.com/cwstryker/robotpy-rev-digit/issues
Project-URL: Source, https://github.com/cwstryker/robotpy-rev-digit
Author-email: Chadwick Stryker <chadwick@stryker5.org>
License-Expression: GPL-3.0-only
License-File: LICENSE.txt
Classifier: Development Status :: 4 - Beta
Classifier: Programming Language :: Python
Classifier: Programming Language :: Python :: 3.8
Classifier: Programming Language :: Python :: 3.9
Classifier: Programming Language :: Python :: 3.10
Classifier: Programming Language :: Python :: 3.11
Classifier: Programming Language :: Python :: 3.12
Classifier: Programming Language :: Python :: Implementation :: CPython
Requires-Python: >=3.12
Requires-Dist: robotpy>=2025.3.2.2
